setup.py
dmerge/__init__.py
dmerge.egg-info/PKG-INFO
dmerge.egg-info/SOURCES.txt
dmerge.egg-info/dependency_links.txt
dmerge.egg-info/not-zip-safe
dmerge.egg-info/top_level.txt