Metadata-Version: 1.0
Name: dmerge
Version: 0.1
Summary: Deep Dict Merge - Recursively merge two dictionaries and return the result
Home-page: http://github.com/edward2a/deep_merge.py
Author: Eduardo A. Paris Penas - Real ReadMe Limited
Author-email: edward2a@gmail.com, epp@realread.me
License: Apache License 2.0
Platform: UNKNOWN
